{
  "_class": "symbolInstance",
  "booleanOperation": -1,
  "clippingMaskMode": 0,
  "do_objectID": "FA1A59CC-2FDB-43B1-9A3D-2DF93B647933",
  "exportOptions": {
    "_class": "exportOptions",
    "do_objectID": "CC6E7617-1758-44D0-B544-C76E70CE610A",
    "exportFormats": [
      {
        "_class": "exportFormat",
        "absoluteSize": 0,
        "fileFormat": "png",
        "name": "",
        "namingScheme": 0,
        "scale": 1,
        "visibleScaleType": 0
      },
      {
        "_class": "exportFormat",
        "absoluteSize": 0,
        "fileFormat": "png",
        "name": "@2x",
        "namingScheme": 0,
        "scale": 2,
        "visibleScaleType": 0
      },
      {
        "_class": "exportFormat",
        "absoluteSize": 0,
        "fileFormat": "png",
        "name": "@3x",
        "namingScheme": 0,
        "scale": 3,
        "visibleScaleType": 0
      }
    ],
    "includedLayerIds": [
    ],
    "layerOptions": 0,
    "shouldTrim": false
  },
  "frame": {
    "_class": "rect",
    "constrainProportions": false,
    "do_objectID": "359C2C68-7312-4665-9C9A-A9DA8AADD39C",
    "height": 48,
    "width": 375,
    "x": 0,
    "y": 475
  },
  "hasClippingMask": false,
  "horizontalSpacing": 0,
  "isFixedToViewport": false,
  "isFlippedHorizontal": false,
  "isFlippedVertical": false,
  "isLocked": false,
  "isVisible": true,
  "layerListExpandedType": 0,
  "name": "list / checkboxOnLight",
  "nameIsFixed": false,
  "overrideValues": [
    {
      "_class": "overrideValue",
      "do_objectID": "1B30F386-5C87-49E5-9161-F2EC66DD26AF",
      "overrideName": "22DD15A7-A22B-441E-9EB6-F49E1E0237C9_stringValue",
      "value": "Business English"
    },
    {
      "_class": "overrideValue",
      "do_objectID": "0C4CBE6C-444C-4413-9EA5-54360B8CAF9A",
      "overrideName": "8A20461C-A21A-4444-AF7E-A1DBE7EEB484/AF6F0313-3991-4D62-A708-4302E8EEB927_symbolID",
      "value": "F3B57E22-6948-47FA-8DE4-2BE828532F84"
    }
  ],
  "resizingConstraint": 13,
  "resizingType": 0,
  "rotation": 0,
  "scale": 1,
  "shouldBreakMaskChain": false,
  "style": {
    "_class": "style",
    "do_objectID": "A5A0EBC7-7439-4DAC-B723-37F82A7F2031",
    "endMarkerType": 0,
    "miterLimit": 10,
    "startMarkerType": 0,
    "windingRule": 1
  },
  "symbolID": "FF197A76-77E7-4A44-9D8E-EF55B53E4E57",
  "verticalSpacing": 0
}