{
  "_class": "text",
  "attributedString": {
    "_class": "attributedString",
    "attributes": [
      {
        "_class": "stringAttribute",
        "attributes": {
          "MSAttributedStringColorAttribute": {
            "_class": "color",
            "alpha": 0.78,
            "blue": 0,
            "green": 0,
            "red": 0
          },
          "MSAttributedStringFontAttribute": {
            "_class": "fontDescriptor",
            "attributes": {
              "name": "Roboto-Bold",
              "size": 16
            }
          },
          "kerning": 0,
          "paragraphStyle": {
            "_class": "paragraphStyle",
            "alignment": 1,
            "maximumLineHeight": 22,
            "minimumLineHeight": 22,
            "paragraphSpacing": 1
          }
        },
        "length": 59,
        "location": 0
      }
    ],
    "string": "I am qualified and prepared to teach these types of lessons"
  },
  "automaticallyDrawOnUnderlyingPath": false,
  "booleanOperation": 0,
  "clippingMaskMode": 0,
  "do_objectID": "6248EE3C-6889-420C-89AC-23A1C7E56E3E",
  "dontSynchroniseWithSymbol": false,
  "exportOptions": {
    "_class": "exportOptions",
    "do_objectID": "1496E272-0B26-49DB-B35A-B50108D8B71A",
    "exportFormats": [
      {
        "_class": "exportFormat",
        "absoluteSize": 0,
        "fileFormat": "png",
        "name": "",
        "namingScheme": 0,
        "scale": 1,
        "visibleScaleType": 0
      }
    ],
    "includedLayerIds": [
    ],
    "layerOptions": 0,
    "shouldTrim": false
  },
  "frame": {
    "_class": "rect",
    "constrainProportions": false,
    "do_objectID": "4490154E-E412-47F2-9DA2-EC75A40EA362",
    "height": 66,
    "width": 164,
    "x": 32,
    "y": 13
  },
  "glyphBounds": "{{2, 4}, {162, 61}}",
  "hasClippingMask": false,
  "isFixedToViewport": false,
  "isFlippedHorizontal": false,
  "isFlippedVertical": false,
  "isLocked": false,
  "isVisible": true,
  "layerListExpandedType": 0,
  "lineSpacingBehaviour": 2,
  "name": "textBold16B78Right",
  "nameIsFixed": true,
  "resizingConstraint": 11,
  "resizingType": 0,
  "rotation": 0,
  "sharedStyleID": "2702A685-D808-415E-AE4C-B01F5F9B4072",
  "shouldBreakMaskChain": false,
  "style": {
    "_class": "style",
    "do_objectID": "A05FD470-CC03-4350-898A-BBA307994FC4",
    "endMarkerType": 0,
    "miterLimit": 10,
    "startMarkerType": 0,
    "textStyle": {
      "_class": "textStyle",
      "do_objectID": "43E6F613-9659-4BA6-82CF-79614E779735",
      "encodedAttributes": {
        "MSAttributedStringColorAttribute": {
          "_class": "color",
          "alpha": 0.78,
          "blue": 0,
          "green": 0,
          "red": 0
        },
        "MSAttributedStringFontAttribute": {
          "_class": "fontDescriptor",
          "attributes": {
            "name": "Roboto-Bold",
            "size": 16
          }
        },
        "kerning": 0,
        "paragraphStyle": {
          "_class": "paragraphStyle",
          "alignment": 1,
          "maximumLineHeight": 22,
          "minimumLineHeight": 22,
          "paragraphSpacing": 1
        }
      },
      "verticalAlignment": 0
    },
    "windingRule": 1
  },
  "textBehaviour": 1
}