{
  "_class": "symbolInstance",
  "booleanOperation": -1,
  "clippingMaskMode": 0,
  "do_objectID": "CC9BFD48-F8A0-4F07-BE92-DC9889BD2452",
  "exportOptions": {
    "_class": "exportOptions",
    "do_objectID": "66ADCAA6-183E-4D01-A305-D3B5BF9D955B",
    "exportFormats": [
      {
        "_class": "exportFormat",
        "absoluteSize": 0,
        "fileFormat": "png",
        "name": "",
        "namingScheme": 0,
        "scale": 1,
        "visibleScaleType": 0
      }
    ],
    "includedLayerIds": [
    ],
    "layerOptions": 0,
    "shouldTrim": false
  },
  "frame": {
    "_class": "rect",
    "constrainProportions": false,
    "do_objectID": "99F59BE9-B0BB-4755-BBE5-F14114B78B85",
    "height": 48,
    "width": 404,
    "x": 204,
    "y": 48
  },
  "hasClippingMask": false,
  "horizontalSpacing": 0,
  "isFixedToViewport": false,
  "isFlippedHorizontal": false,
  "isFlippedVertical": false,
  "isLocked": false,
  "isVisible": true,
  "layerListExpandedType": 0,
  "name": "list / checkboxWhite",
  "nameIsFixed": false,
  "overrideValues": [
    {
      "_class": "overrideValue",
      "do_objectID": "489C6757-5210-4B25-8CE6-1AD6518C2FD6",
      "overrideName": "6FB1EB37-BCC7-47BB-AE5F-92EFF8A2E2CF_stringValue",
      "value": "Business English"
    }
  ],
  "resizingConstraint": 14,
  "resizingType": 0,
  "rotation": 0,
  "scale": 1,
  "shouldBreakMaskChain": false,
  "style": {
    "_class": "style",
    "do_objectID": "87F4E749-7D71-49E2-970C-8F4138826CE7",
    "endMarkerType": 0,
    "miterLimit": 10,
    "startMarkerType": 0,
    "windingRule": 1
  },
  "symbolID": "DBC107D4-040F-4672-90AF-904C77AC8904",
  "verticalSpacing": 0
}