{
  "_class": "symbolInstance",
  "booleanOperation": -1,
  "clippingMaskMode": 0,
  "do_objectID": "5091B30F-1C7A-4F92-98CF-616D00F9EB55",
  "exportOptions": {
    "_class": "exportOptions",
    "do_objectID": "725C8CFF-6194-4616-966C-574BC8B9B52A",
    "exportFormats": [
      {
        "_class": "exportFormat",
        "absoluteSize": 0,
        "fileFormat": "png",
        "name": "",
        "namingScheme": 0,
        "scale": 1,
        "visibleScaleType": 0
      },
      {
        "_class": "exportFormat",
        "absoluteSize": 0,
        "fileFormat": "png",
        "name": "@2x",
        "namingScheme": 0,
        "scale": 2,
        "visibleScaleType": 0
      },
      {
        "_class": "exportFormat",
        "absoluteSize": 0,
        "fileFormat": "png",
        "name": "@3x",
        "namingScheme": 0,
        "scale": 3,
        "visibleScaleType": 0
      }
    ],
    "includedLayerIds": [
    ],
    "layerOptions": 0,
    "shouldTrim": false
  },
  "frame": {
    "_class": "rect",
    "constrainProportions": false,
    "do_objectID": "92A126EF-93B5-479A-9B8D-E7EC31EB70C4",
    "height": 48,
    "width": 375,
    "x": 0,
    "y": 76
  },
  "hasClippingMask": false,
  "horizontalSpacing": 0,
  "isFixedToViewport": false,
  "isFlippedHorizontal": false,
  "isFlippedVertical": false,
  "isLocked": false,
  "isVisible": true,
  "layerListExpandedType": 0,
  "name": "list / title48",
  "nameIsFixed": false,
  "overrideValues": [
    {
      "_class": "overrideValue",
      "do_objectID": "FE481C23-C460-4675-8EF9-04E41DACFAC0",
      "overrideName": "D9C89AAE-303A-40DF-8EB7-A7055800E2D4_stringValue",
      "value": "Vocabulary / Expressions"
    },
    {
      "_class": "overrideValue",
      "do_objectID": "F1077B71-3DD7-4D9B-A1D5-1334DFF7B52D",
      "overrideName": "43069067-0859-4B4F-B14B-248099C11F84_symbolID",
      "value": ""
    }
  ],
  "resizingConstraint": 13,
  "resizingType": 0,
  "rotation": 0,
  "scale": 1,
  "shouldBreakMaskChain": false,
  "style": {
    "_class": "style",
    "do_objectID": "71A6B1E1-E1E0-49C0-A0FA-9B42E78F50ED",
    "endMarkerType": 0,
    "miterLimit": 10,
    "startMarkerType": 0,
    "windingRule": 1
  },
  "symbolID": "78024422-ABFA-460B-9D59-D448102F428D",
  "verticalSpacing": 0
}