{
  "_class": "page",
  "booleanOperation": -1,
  "clippingMaskMode": 0,
  "do_objectID": "D7A6CEFF-BD72-41BF-B473-E4771802C6AE",
  "exportOptions": {
    "_class": "exportOptions",
    "exportFormats": [
    ],
    "includedLayerIds": [
    ],
    "layerOptions": 0,
    "shouldTrim": false
  },
  "frame": {
    "_class": "rect",
    "constrainProportions": false,
    "height": 0,
    "width": 0,
    "x": 0,
    "y": 0
  },
  "groupLayout": {
    "_class": "MSImmutableFreeformGroupLayout"
  },
  "hasClickThrough": true,
  "hasClippingMask": false,
  "horizontalRulerData": {
    "_class": "rulerData",
    "base": -560,
    "guides": [
    ]
  },
  "includeInCloudUpload": true,
  "isFixedToViewport": false,
  "isFlippedHorizontal": false,
  "isFlippedVertical": false,
  "isLocked": false,
  "isVisible": true,
  "layerListExpandedType": 0,
  "layers": [
    {
      "class": "artboard",
      "id": "D23D394B-1C5F-4263-97E2-D6D2D3937FAF"
    },
    {
      "class": "symbolMaster",
      "id": "E3737668-450E-4D62-BB65-8AB03E97342C"
    },
    {
      "class": "artboard",
      "id": "552B9D2D-B686-4F38-A340-E77C86F00FA1"
    },
    {
      "class": "artboard",
      "id": "F78759CB-92D2-4692-9082-FE4997530E2F"
    },
    {
      "class": "artboard",
      "id": "A436B7DE-6E7C-47DA-9236-1331A2D53AE8"
    },
    {
      "class": "artboard",
      "id": "E75F7384-302B-40D7-A7A3-2E9175D6360C"
    },
    {
      "class": "artboard",
      "id": "10CE2BB5-AF9F-4AA0-BC3B-02910B265E2B"
    },
    {
      "class": "artboard",
      "id": "593037FF-0A78-4D26-B883-E7993349C01B"
    },
    {
      "class": "artboard",
      "id": "172614AF-4CE9-4DF6-AD6B-BB13B17933B3"
    },
    {
      "class": "artboard",
      "id": "94C04E38-4E9B-4B47-B7B3-819486C975AE"
    },
    {
      "class": "artboard",
      "id": "19947E92-7895-4D11-A211-8CCB8627E49A"
    },
    {
      "class": "artboard",
      "id": "5F82F360-4E71-41B3-A529-7049BAA7F195"
    },
    {
      "class": "artboard",
      "id": "2E31DDED-F80D-4198-91A8-793B5B5746B9"
    },
    {
      "class": "artboard",
      "id": "96598EEA-5283-44CD-904B-A474FBA8FF55"
    },
    {
      "class": "artboard",
      "id": "DA95BB57-768D-4760-845B-B7B86CB0F1B2"
    },
    {
      "class": "artboard",
      "id": "CED93D03-21CC-421B-8653-55907B66D53E"
    },
    {
      "class": "artboard",
      "id": "FD0698BE-9DD2-467D-B32C-26C3D5431D99"
    },
    {
      "class": "artboard",
      "id": "9151D6EA-341E-491C-A065-F948029B8F7C"
    },
    {
      "class": "symbolMaster",
      "id": "3CF7FB13-5206-48CF-B75C-7742F4B7AB9A"
    },
    {
      "class": "artboard",
      "id": "78E4B288-355A-4AE8-978E-373E2A858E88"
    },
    {
      "class": "artboard",
      "id": "632C9B86-38A0-4025-BD4F-4C4750973C65"
    },
    {
      "class": "artboard",
      "id": "2AA459D8-78CA-42C1-978F-FB54FB0B1769"
    },
    {
      "class": "artboard",
      "id": "841C0990-DF46-4011-9A63-BE7B30FC52E1"
    },
    {
      "class": "artboard",
      "id": "23CB1FF2-3373-4AD1-9D13-8FB50BFE7E53"
    },
    {
      "class": "artboard",
      "id": "06910941-9DE7-415D-889D-8B2016911E5F"
    },
    {
      "class": "artboard",
      "id": "336C009B-024E-4286-A464-45E2303308F4"
    },
    {
      "class": "artboard",
      "id": "87EB1710-D9CC-44B6-99AF-CAAA2EF03924"
    },
    {
      "class": "symbolMaster",
      "id": "C7EDB501-4710-4D06-B6F1-17370741EC1C"
    }
  ],
  "name": "settings",
  "nameIsFixed": true,
  "resizingConstraint": 63,
  "resizingType": 0,
  "rotation": 0,
  "shouldBreakMaskChain": false,
  "style": {
    "_class": "style",
    "endMarkerType": 0,
    "miterLimit": 10,
    "startMarkerType": 0,
    "windingRule": 1
  },
  "verticalRulerData": {
    "_class": "rulerData",
    "base": -472,
    "guides": [
    ]
  }
}