{
  "_class": "artboard",
  "backgroundColor": {
    "_class": "color",
    "alpha": 1,
    "blue": 1,
    "do_objectID": "2C266867-F5A7-4A7D-9988-E6F33DF227D5",
    "green": 0.3019607843137255,
    "red": 0.5176470588235293
  },
  "booleanOperation": -1,
  "clippingMaskMode": 0,
  "do_objectID": "6249E57C-B7E7-46CC-A7F3-C9CE1C02EE3A",
  "exportOptions": {
    "_class": "exportOptions",
    "do_objectID": "4E01DD5C-BBFE-4358-983D-7DECE6DCEEC3",
    "exportFormats": [
    ],
    "includedLayerIds": [
    ],
    "layerOptions": 0,
    "shouldTrim": false
  },
  "frame": {
    "_class": "rect",
    "constrainProportions": false,
    "do_objectID": "1E3B18F5-5213-49E0-A98D-2521707D62F9",
    "height": 640,
    "width": 360,
    "x": -102,
    "y": 268
  },
  "groupLayout": {
    "_class": "MSImmutableFreeformGroupLayout",
    "do_objectID": "9E40F0F6-374A-4550-94D2-250FE92780FF"
  },
  "hasBackgroundColor": true,
  "hasClickThrough": true,
  "hasClippingMask": false,
  "horizontalRulerData": {
    "_class": "rulerData",
    "base": 0,
    "do_objectID": "49B3FD51-0413-42B4-A095-CB1B627ABF71",
    "guides": [
    ]
  },
  "includeBackgroundColorInExport": true,
  "includeInCloudUpload": true,
  "isFixedToViewport": false,
  "isFlippedHorizontal": false,
  "isFlippedVertical": false,
  "isFlowHome": false,
  "isLocked": false,
  "isVisible": true,
  "layerListExpandedType": 2,
  "layers": [
    {
      "class": "symbolInstance",
      "id": "5A0F50EC-D96B-4F31-8960-1854B11746D1"
    },
    {
      "class": "rectangle",
      "id": "16ABDA3F-15E6-4131-BD60-8E2019202F0A"
    },
    {
      "class": "text",
      "id": "8FF9C71A-91AD-46C4-ACDD-C537935D5358"
    },
    {
      "class": "rectangle",
      "id": "1CC8C944-6B53-4967-ABFE-6601D0634403"
    },
    {
      "class": "text",
      "id": "5298A52B-59E2-462F-A9D0-E97F935790B1"
    },
    {
      "class": "rectangle",
      "id": "FCE7F9AC-349C-4AD8-AB35-5552D4FC8E92"
    },
    {
      "class": "text",
      "id": "9F2D162D-8FE5-42BD-B527-48EBE9458F94"
    },
    {
      "class": "rectangle",
      "id": "6B897BA0-D774-4520-A7A9-2B0E2633C5FA"
    },
    {
      "class": "text",
      "id": "9FDB7A44-E6EA-465E-8974-A9BE63532561"
    },
    {
      "class": "text",
      "id": "22E55982-070C-4F6E-A1C2-D4D8A8B09962"
    },
    {
      "class": "symbolInstance",
      "id": "55F00F96-42D0-478C-8E99-EAA8AE266C64"
    },
    {
      "class": "rectangle",
      "id": "44953323-9ED5-46FF-A181-C53CCE2818ED"
    },
    {
      "class": "text",
      "id": "43B414A7-C9D4-4BDF-A672-FA1B1C62B4AF"
    },
    {
      "class": "rectangle",
      "id": "94B856B7-280F-4097-B5B9-CEF347A8033E"
    },
    {
      "class": "text",
      "id": "31A8415F-F06C-4BA7-97C4-5E5ABCAF822D"
    },
    {
      "class": "symbolInstance",
      "id": "8FFBBC2B-CB7F-4416-9015-BBFF9E7A64EA"
    },
    {
      "class": "rectangle",
      "id": "2EAE58BF-EBFB-4F2E-B82C-883EF6D4D6F2"
    },
    {
      "class": "text",
      "id": "132ADF5C-B979-4AD9-89C4-C6DF70640306"
    },
    {
      "class": "rectangle",
      "id": "1F925C20-FD46-4091-9221-0C5C3B8A4348"
    },
    {
      "class": "text",
      "id": "852B8BC2-7329-4EA4-85CC-82B0A128A50D"
    },
    {
      "class": "rectangle",
      "id": "02FAD93D-E63D-4B7A-9980-049BB4619101"
    },
    {
      "class": "text",
      "id": "1484C3C5-4B81-4C3A-9B07-3C90705B1B2F"
    },
    {
      "class": "rectangle",
      "id": "DD188B6E-DEA4-499F-9578-E45022C86202"
    },
    {
      "class": "symbolInstance",
      "id": "807129D2-0E63-4869-9782-C54F6A4FA45E"
    },
    {
      "class": "symbolInstance",
      "id": "728BD60C-7513-464B-9C2D-FFA87BEB46B1"
    },
    {
      "class": "symbolInstance",
      "id": "CC666F37-1F97-43FC-9B29-86BBD3BFB62A"
    },
    {
      "class": "symbolInstance",
      "id": "F422CC55-2EB1-4C7A-B874-34407F5BEB82"
    }
  ],
  "name": "settings / messages / details",
  "nameIsFixed": true,
  "presetDictionary": {
    "allowResizedMatching": 0,
    "height": 640,
    "name": "Android",
    "offersLandscapeVariant": 1,
    "width": 360
  },
  "resizesContent": true,
  "resizingConstraint": 63,
  "resizingType": 0,
  "rotation": 0,
  "shouldBreakMaskChain": true,
  "style": {
    "_class": "style",
    "do_objectID": "851AD913-2983-480B-BF61-707F2EF150A6",
    "endMarkerType": 0,
    "miterLimit": 10,
    "startMarkerType": 0,
    "windingRule": 1
  },
  "verticalRulerData": {
    "_class": "rulerData",
    "base": 0,
    "do_objectID": "46F74534-60F3-4E31-87BC-387A6BAE9C9A",
    "guides": [
    ]
  }
}