{
  "_class": "symbolInstance",
  "booleanOperation": -1,
  "clippingMaskMode": 0,
  "do_objectID": "E60EAC6A-9A0C-4A1E-B365-B1AE1A33320F",
  "exportOptions": {
    "_class": "exportOptions",
    "exportFormats": [
      {
        "_class": "exportFormat",
        "absoluteSize": 0,
        "fileFormat": "png",
        "name": "",
        "namingScheme": 0,
        "scale": 1,
        "visibleScaleType": 0
      },
      {
        "_class": "exportFormat",
        "absoluteSize": 0,
        "fileFormat": "png",
        "name": "@2x",
        "namingScheme": 0,
        "scale": 2,
        "visibleScaleType": 0
      },
      {
        "_class": "exportFormat",
        "absoluteSize": 0,
        "fileFormat": "png",
        "name": "@3x",
        "namingScheme": 0,
        "scale": 3,
        "visibleScaleType": 0
      }
    ],
    "includedLayerIds": [
    ],
    "layerOptions": 0,
    "shouldTrim": false
  },
  "frame": {
    "_class": "rect",
    "constrainProportions": false,
    "height": 164,
    "width": 375,
    "x": 0,
    "y": 468
  },
  "hasClippingMask": false,
  "horizontalSpacing": 0,
  "isFixedToViewport": false,
  "isFlippedHorizontal": false,
  "isFlippedVertical": false,
  "isLocked": false,
  "isVisible": true,
  "layerListExpandedType": 0,
  "name": "list / cities / attractions copy",
  "nameIsFixed": false,
  "overrideValues": [
    {
      "_class": "overrideValue",
      "overrideName": "8E025D53-6C49-4945-888E-EC23058DC94D_image",
      "value": {
        "_class": "MSJSONFileReference",
        "_ref": "images/a5d474c7bd7460eacecb09171d03c5f81b0b5675.png",
        "_ref_class": "MSImageData"
      }
    },
    {
      "_class": "overrideValue",
      "overrideName": "1A505220-74B2-49B6-BC03-DE7E18CC7670_stringValue",
      "value": "Getty Museum"
    }
  ],
  "resizingConstraint": 63,
  "resizingType": 0,
  "rotation": 0,
  "scale": 1,
  "shouldBreakMaskChain": false,
  "style": {
    "_class": "style",
    "endMarkerType": 0,
    "miterLimit": 10,
    "startMarkerType": 0,
    "windingRule": 1
  },
  "symbolID": "E38B48B4-3EE2-43F0-8DDA-F590AA7C6836",
  "userInfo": {
    "unsplash": {
      "unsplash.search.term": "\"Getty Museum\""
    }
  },
  "verticalSpacing": 0
}