{
  "_class": "symbolInstance",
  "booleanOperation": -1,
  "clippingMaskMode": 0,
  "do_objectID": "84E902C1-F3C4-4486-808E-045803A85F22",
  "exportOptions": {
    "_class": "exportOptions",
    "do_objectID": "3A505925-2540-4846-892E-2B8457B2A02E",
    "exportFormats": [
      {
        "_class": "exportFormat",
        "absoluteSize": 0,
        "fileFormat": "png",
        "name": "",
        "namingScheme": 0,
        "scale": 1,
        "visibleScaleType": 0
      }
    ],
    "includedLayerIds": [
    ],
    "layerOptions": 0,
    "shouldTrim": false
  },
  "frame": {
    "_class": "rect",
    "constrainProportions": false,
    "do_objectID": "1078EB9D-42AA-4E77-BE9D-7C6134943752",
    "height": 29,
    "width": 960,
    "x": 0,
    "y": 694
  },
  "hasClippingMask": false,
  "horizontalSpacing": 0,
  "isFixedToViewport": false,
  "isFlippedHorizontal": false,
  "isFlippedVertical": false,
  "isLocked": false,
  "isVisible": true,
  "layerListExpandedType": 0,
  "name": "calendar / row / time",
  "nameIsFixed": false,
  "overrideValues": [
    {
      "_class": "overrideValue",
      "do_objectID": "3F87C699-81B3-47A1-851C-8AFE705BC238",
      "overrideName": "31C630DC-2E26-4D87-A4D6-B9A723E97596/D01E5F6E-0211-4D5A-9FA2-A9F6331CC282_stringValue",
      "value": "10:00 PM"
    }
  ],
  "resizingConstraint": 18,
  "resizingType": 0,
  "rotation": 0,
  "scale": 1,
  "shouldBreakMaskChain": false,
  "style": {
    "_class": "style",
    "do_objectID": "5DB40BBB-DCE7-4E1D-A3D7-032DA402F5D7",
    "endMarkerType": 0,
    "miterLimit": 10,
    "startMarkerType": 0,
    "windingRule": 1
  },
  "symbolID": "EFBBDF08-E42D-4F4B-9396-04D2441101C3",
  "verticalSpacing": 0
}