{
  "_class": "symbolMaster",
  "allowsOverrides": true,
  "backgroundColor": {
    "_class": "color",
    "alpha": 0.54,
    "blue": 0,
    "green": 0,
    "red": 0
  },
  "booleanOperation": -1,
  "changeIdentifier": 921,
  "clippingMaskMode": 0,
  "do_objectID": "B94C608D-9F87-474E-B5CE-9CFBA947E1C7",
  "exportOptions": {
    "_class": "exportOptions",
    "do_objectID": "E14B67E3-2E9E-44F2-84BC-F48CEE9DF796",
    "exportFormats": [
      {
        "_class": "exportFormat",
        "absoluteSize": 0,
        "fileFormat": "png",
        "name": "",
        "namingScheme": 0,
        "scale": 1,
        "visibleScaleType": 0
      }
    ],
    "includedLayerIds": [
    ],
    "layerOptions": 0,
    "shouldTrim": false
  },
  "frame": {
    "_class": "rect",
    "constrainProportions": false,
    "do_objectID": "30AE59D4-54F3-45E5-BEF8-58EE768652B2",
    "height": 218,
    "width": 218,
    "x": 6937,
    "y": -56
  },
  "groupLayout": {
    "_class": "MSImmutableFreeformGroupLayout",
    "do_objectID": "D57637CF-F403-45FC-B9CF-3E7F3DDB01A8"
  },
  "hasBackgroundColor": true,
  "hasClickThrough": true,
  "hasClippingMask": false,
  "horizontalRulerData": {
    "_class": "rulerData",
    "base": 0,
    "do_objectID": "504A4B52-59D0-4DE7-A2F0-3D4846A05979",
    "guides": [
    ]
  },
  "includeBackgroundColorInExport": true,
  "includeBackgroundColorInInstance": true,
  "includeInCloudUpload": true,
  "isFixedToViewport": false,
  "isFlippedHorizontal": false,
  "isFlippedVertical": false,
  "isFlowHome": false,
  "isLocked": false,
  "isVisible": true,
  "layerListExpandedType": 2,
  "layers": [
    {
      "class": "shapeGroup",
      "id": "0054C0E8-FBB4-40BE-8B61-B69B898D3C40"
    }
  ],
  "name": "library / status / delete",
  "nameIsFixed": true,
  "overrideProperties": [
  ],
  "resizesContent": true,
  "resizingConstraint": 63,
  "resizingType": 0,
  "rotation": 0,
  "shouldBreakMaskChain": true,
  "style": {
    "_class": "style",
    "do_objectID": "B345C343-890D-4D09-A1E4-599686111178",
    "endMarkerType": 0,
    "miterLimit": 10,
    "startMarkerType": 0,
    "windingRule": 1
  },
  "symbolID": "BB4D2CE5-D2D9-4369-821E-1042359D18A2",
  "verticalRulerData": {
    "_class": "rulerData",
    "base": 0,
    "do_objectID": "4EE4CBFB-B94C-4356-9869-CC7069263A8E",
    "guides": [
    ]
  }
}