{
  "_class": "symbolMaster",
  "allowsOverrides": true,
  "backgroundColor": {
    "_class": "color",
    "alpha": 1,
    "blue": 0,
    "do_objectID": "50B4E214-23BF-4B6D-908D-8F7BB0079BCB",
    "green": 0,
    "red": 0
  },
  "booleanOperation": 0,
  "changeIdentifier": 5385,
  "clippingMaskMode": 0,
  "do_objectID": "8D7586AC-59C6-47DE-8391-485767E1964B",
  "exportOptions": {
    "_class": "exportOptions",
    "do_objectID": "BC368084-F679-4CF1-A7E1-79DD13C4CA21",
    "exportFormats": [
      {
        "_class": "exportFormat",
        "absoluteSize": 0,
        "fileFormat": "png",
        "name": "",
        "namingScheme": 0,
        "scale": 1,
        "visibleScaleType": 0
      },
      {
        "_class": "exportFormat",
        "absoluteSize": 0,
        "fileFormat": "png",
        "name": "@2x",
        "namingScheme": 0,
        "scale": 2,
        "visibleScaleType": 0
      },
      {
        "_class": "exportFormat",
        "absoluteSize": 0,
        "fileFormat": "png",
        "name": "@3x",
        "namingScheme": 0,
        "scale": 3,
        "visibleScaleType": 0
      }
    ],
    "includedLayerIds": [
    ],
    "layerOptions": 0,
    "shouldTrim": false
  },
  "frame": {
    "_class": "rect",
    "constrainProportions": false,
    "do_objectID": "766011F0-0122-4F3B-89E1-01CA2B842736",
    "height": 28,
    "width": 28,
    "x": -560,
    "y": 1586
  },
  "groupLayout": {
    "_class": "MSImmutableFreeformGroupLayout",
    "do_objectID": "AAE8C538-D93E-48DD-94A2-FAB3F72F04D8"
  },
  "hasBackgroundColor": true,
  "hasClickThrough": false,
  "hasClippingMask": false,
  "horizontalRulerData": {
    "_class": "rulerData",
    "base": 0,
    "do_objectID": "BDE0A03E-9070-4BD9-917B-BE6AF3311167",
    "guides": [
    ]
  },
  "includeBackgroundColorInExport": false,
  "includeBackgroundColorInInstance": false,
  "includeInCloudUpload": true,
  "isFixedToViewport": false,
  "isFlippedHorizontal": false,
  "isFlippedVertical": false,
  "isFlowHome": false,
  "isLocked": false,
  "isVisible": true,
  "layerListExpandedType": 2,
  "layers": [
    {
      "class": "symbolInstance",
      "id": "55402A35-03B5-483A-82F2-AA092DAF6036"
    }
  ],
  "name": "btn / lessonOnDark / icCamOn",
  "nameIsFixed": true,
  "originalObjectID": "F7AA7B6A-81F1-443C-80F5-0F46FE73B0BE",
  "overrideProperties": [
  ],
  "resizesContent": true,
  "resizingConstraint": 63,
  "resizingType": 0,
  "rotation": 0,
  "shouldBreakMaskChain": true,
  "style": {
    "_class": "style",
    "do_objectID": "519261C2-F7EC-46CD-A605-DA2244179111",
    "endMarkerType": 0,
    "miterLimit": 10,
    "startMarkerType": 0,
    "windingRule": 1
  },
  "symbolID": "7CF3F43A-A560-43CE-ADA0-C5E2948A1781",
  "userInfo": {
    "avocode": {
      "idsFixed": 1
    }
  },
  "verticalRulerData": {
    "_class": "rulerData",
    "base": 0,
    "do_objectID": "1CDE4681-5229-4D33-BCBB-DD98597BE38A",
    "guides": [
    ]
  }
}