{
  "_class": "text",
  "attributedString": {
    "_class": "attributedString",
    "attributes": [
      {
        "_class": "stringAttribute",
        "attributes": {
          "MSAttributedStringColorAttribute": {
            "_class": "color",
            "alpha": 0.54,
            "blue": 0,
            "green": 0,
            "red": 0
          },
          "MSAttributedStringFontAttribute": {
            "_class": "fontDescriptor",
            "attributes": {
              "name": "Roboto-Regular",
              "size": 16
            }
          },
          "kerning": 0,
          "paragraphStyle": {
            "_class": "paragraphStyle",
            "alignment": 0,
            "maximumLineHeight": 22,
            "minimumLineHeight": 22,
            "paragraphSpacing": 1
          }
        },
        "length": 248,
        "location": 0
      }
    ],
    "string": "Thanks for signing up as a tutor!\n\nYour new account is under review.\nWe'll e-mail you after your account has been enabled.\n\nTo edit your profile, click HERE.\n\nAfter your account is enabled,\nyou'll be able to video chat with students from this page."
  },
  "automaticallyDrawOnUnderlyingPath": false,
  "booleanOperation": 0,
  "clippingMaskMode": 0,
  "do_objectID": "A5101A85-765A-4682-AA62-31B833028028",
  "dontSynchroniseWithSymbol": false,
  "exportOptions": {
    "_class": "exportOptions",
    "do_objectID": "AAB04E7D-D5A3-4353-A5E1-07F82D201069",
    "exportFormats": [
      {
        "_class": "exportFormat",
        "absoluteSize": 0,
        "fileFormat": "png",
        "name": "",
        "namingScheme": 0,
        "scale": 1,
        "visibleScaleType": 0
      }
    ],
    "includedLayerIds": [
    ],
    "layerOptions": 0,
    "shouldTrim": false
  },
  "frame": {
    "_class": "rect",
    "constrainProportions": false,
    "do_objectID": "E35D4415-95FE-4C0E-99BA-2C8395E0CE34",
    "height": 206,
    "width": 576,
    "x": 432,
    "y": 208
  },
  "glyphBounds": "{{0, 4}, {404, 201}}",
  "hasClippingMask": false,
  "isFixedToViewport": false,
  "isFlippedHorizontal": false,
  "isFlippedVertical": false,
  "isLocked": false,
  "isVisible": true,
  "layerListExpandedType": 0,
  "lineSpacingBehaviour": 2,
  "name": "textRegular16B54Left",
  "nameIsFixed": true,
  "resizingConstraint": 10,
  "resizingType": 0,
  "rotation": 0,
  "sharedStyleID": "0650C9FD-DDC4-43A6-84F4-58C598F798FF",
  "shouldBreakMaskChain": false,
  "style": {
    "_class": "style",
    "do_objectID": "F668C41D-343B-45BA-ADC2-2C0D581B12FC",
    "endMarkerType": 0,
    "miterLimit": 10,
    "startMarkerType": 0,
    "textStyle": {
      "_class": "textStyle",
      "do_objectID": "06241AEC-79BC-44DA-8781-6FEE33650A30",
      "encodedAttributes": {
        "MSAttributedStringColorAttribute": {
          "_class": "color",
          "alpha": 0.54,
          "blue": 0,
          "green": 0,
          "red": 0
        },
        "MSAttributedStringFontAttribute": {
          "_class": "fontDescriptor",
          "attributes": {
            "name": "Roboto-Regular",
            "size": 16
          }
        },
        "kerning": 0,
        "paragraphStyle": {
          "_class": "paragraphStyle",
          "alignment": 0,
          "maximumLineHeight": 22,
          "minimumLineHeight": 22,
          "paragraphSpacing": 1
        }
      },
      "verticalAlignment": 0
    },
    "windingRule": 1
  },
  "textBehaviour": 1
}