{
  "_class": "symbolInstance",
  "booleanOperation": -1,
  "clippingMaskMode": 0,
  "do_objectID": "C78D7B05-B67C-4179-B8D3-732E1AE8A64E",
  "exportOptions": {
    "_class": "exportOptions",
    "do_objectID": "2A28BC36-442B-4E41-8C2A-6A95205C3E1E",
    "exportFormats": [
      {
        "_class": "exportFormat",
        "absoluteSize": 0,
        "fileFormat": "png",
        "name": "",
        "namingScheme": 0,
        "scale": 1,
        "visibleScaleType": 0
      },
      {
        "_class": "exportFormat",
        "absoluteSize": 0,
        "fileFormat": "png",
        "name": "@2x",
        "namingScheme": 0,
        "scale": 2,
        "visibleScaleType": 0
      },
      {
        "_class": "exportFormat",
        "absoluteSize": 0,
        "fileFormat": "png",
        "name": "@3x",
        "namingScheme": 0,
        "scale": 3,
        "visibleScaleType": 0
      }
    ],
    "includedLayerIds": [
    ],
    "layerOptions": 0,
    "shouldTrim": false
  },
  "frame": {
    "_class": "rect",
    "constrainProportions": false,
    "do_objectID": "ADAA86F3-61D9-45AF-B55F-B27CEF178DA4",
    "height": 56,
    "width": 375,
    "x": 0,
    "y": 611
  },
  "hasClippingMask": false,
  "horizontalSpacing": 0,
  "isFixedToViewport": false,
  "isFlippedHorizontal": false,
  "isFlippedVertical": false,
  "isLocked": false,
  "isVisible": true,
  "layerListExpandedType": 0,
  "name": "btn / basicFullWhite",
  "nameIsFixed": false,
  "overrideValues": [
    {
      "_class": "overrideValue",
      "do_objectID": "069FA652-944D-4B12-8438-6CAD6970FBF6",
      "overrideName": "E1930392-2F44-47B8-9BA2-65C71C0BA4F5_stringValue",
      "value": "Start your first lesson"
    }
  ],
  "resizingConstraint": 13,
  "resizingType": 0,
  "rotation": 0,
  "scale": 1,
  "shouldBreakMaskChain": false,
  "style": {
    "_class": "style",
    "do_objectID": "467D8859-0D71-40F7-8081-BEBEE78EAB72",
    "endMarkerType": 0,
    "miterLimit": 10,
    "startMarkerType": 0,
    "windingRule": 1
  },
  "symbolID": "6E47714A-0B05-4263-93ED-715B6D094EA2",
  "verticalSpacing": 0
}