{
  "_class": "symbolMaster",
  "backgroundColor": {
    "_class": "color",
    "alpha": 1,
    "blue": 1,
    "do_objectID": "C7EBFF71-D5EB-4F1A-A106-74BC9EB7B771",
    "green": 0.3008003048780488,
    "red": 0.5166644590046954
  },
  "booleanOperation": 0,
  "changeIdentifier": 4945,
  "clippingMaskMode": 0,
  "do_objectID": "8AE7C4F7-CDB3-49F4-AAB3-B060E3BCB1E6",
  "exportOptions": {
    "_class": "exportOptions",
    "do_objectID": "E67E4C10-547B-4E70-A262-51C5DF6D44C6",
    "exportFormats": [
      {
        "_class": "exportFormat",
        "absoluteSize": 0,
        "fileFormat": "png",
        "name": "",
        "namingScheme": 0,
        "scale": 1,
        "visibleScaleType": 0
      },
      {
        "_class": "exportFormat",
        "absoluteSize": 0,
        "fileFormat": "png",
        "name": "@2x",
        "namingScheme": 0,
        "scale": 2,
        "visibleScaleType": 0
      },
      {
        "_class": "exportFormat",
        "absoluteSize": 0,
        "fileFormat": "png",
        "name": "@3x",
        "namingScheme": 0,
        "scale": 3,
        "visibleScaleType": 0
      }
    ],
    "includedLayerIds": [
    ],
    "layerOptions": 0,
    "shouldTrim": false
  },
  "frame": {
    "_class": "rect",
    "constrainProportions": false,
    "do_objectID": "CC4FD484-48E9-4EA5-B765-712F59363F74",
    "height": 48,
    "width": 375,
    "x": 390,
    "y": 8
  },
  "groupLayout": {
    "_class": "MSImmutableFreeformGroupLayout",
    "do_objectID": "A7BA2FF4-7EC6-447E-A325-0F0201953197"
  },
  "hasBackgroundColor": false,
  "hasClickThrough": false,
  "hasClippingMask": false,
  "horizontalRulerData": {
    "_class": "rulerData",
    "base": 0,
    "do_objectID": "86DDA550-43B5-4893-AFA3-6A553429BFA2",
    "guides": [
    ]
  },
  "includeBackgroundColorInExport": false,
  "includeBackgroundColorInInstance": false,
  "includeInCloudUpload": true,
  "isFixedToViewport": false,
  "isFlippedHorizontal": false,
  "isFlippedVertical": false,
  "isFlowHome": false,
  "isLocked": false,
  "isVisible": true,
  "layerListExpandedType": 2,
  "layers": [
    {
      "class": "text",
      "id": "78187E92-427B-46F6-A85D-63AF3B08D7FF"
    }
  ],
  "name": "list / title48OnLight",
  "nameIsFixed": true,
  "originalObjectID": "F7AA7B6A-81F1-443C-80F5-0F46FE73B0BE",
  "overrideProperties": [
    {
      "_class": "MSImmutableOverrideProperty",
      "canOverride": true,
      "overrideName": "78187E92-427B-46F6-A85D-63AF3B08D7FF_textStyle"
    },
    {
      "_class": "MSImmutableOverrideProperty",
      "canOverride": true,
      "overrideName": "78187E92-427B-46F6-A85D-63AF3B08D7FF_stringValue"
    }
  ],
  "resizesContent": true,
  "resizingConstraint": 63,
  "resizingType": 0,
  "rotation": 0,
  "shouldBreakMaskChain": true,
  "style": {
    "_class": "style",
    "do_objectID": "72A3515C-B24B-4908-A913-6CFBD94B10A1",
    "endMarkerType": 0,
    "miterLimit": 10,
    "startMarkerType": 0,
    "windingRule": 1
  },
  "symbolID": "C7E28591-6D5E-479E-B260-279B1B5AA706",
  "userInfo": {
    "avocode": {
      "idsFixed": 1
    }
  },
  "verticalRulerData": {
    "_class": "rulerData",
    "base": 0,
    "do_objectID": "3BFA6185-3B8B-4701-91FC-3AF591E49BF5",
    "guides": [
    ]
  }
}