{
  "_class": "symbolInstance",
  "booleanOperation": -1,
  "clippingMaskMode": 0,
  "do_objectID": "43250452-6A7C-4816-8734-EE78FACDCE80",
  "exportOptions": {
    "_class": "exportOptions",
    "do_objectID": "0DFA7B6E-8F33-4C98-9B5C-3DA36A9F0830",
    "exportFormats": [
      {
        "_class": "exportFormat",
        "absoluteSize": 0,
        "fileFormat": "png",
        "name": "mdpi/",
        "namingScheme": 1,
        "scale": 1,
        "visibleScaleType": 0
      },
      {
        "_class": "exportFormat",
        "absoluteSize": 0,
        "fileFormat": "png",
        "name": "hdpi/",
        "namingScheme": 1,
        "scale": 1.5,
        "visibleScaleType": 0
      },
      {
        "_class": "exportFormat",
        "absoluteSize": 0,
        "fileFormat": "png",
        "name": "xhdpi/",
        "namingScheme": 1,
        "scale": 2,
        "visibleScaleType": 0
      },
      {
        "_class": "exportFormat",
        "absoluteSize": 0,
        "fileFormat": "png",
        "name": "xxhdpi/",
        "namingScheme": 1,
        "scale": 3,
        "visibleScaleType": 0
      },
      {
        "_class": "exportFormat",
        "absoluteSize": 0,
        "fileFormat": "png",
        "name": "xxxhdpi/",
        "namingScheme": 1,
        "scale": 4,
        "visibleScaleType": 0
      }
    ],
    "includedLayerIds": [
    ],
    "layerOptions": 0,
    "shouldTrim": false
  },
  "frame": {
    "_class": "rect",
    "constrainProportions": false,
    "do_objectID": "A5826D1F-2A42-4396-84FB-5D6B7AAA69B0",
    "height": 64,
    "width": 360,
    "x": 0,
    "y": 448
  },
  "hasClippingMask": false,
  "horizontalSpacing": 0,
  "isFixedToViewport": false,
  "isFlippedHorizontal": false,
  "isFlippedVertical": false,
  "isLocked": false,
  "isVisible": true,
  "layerListExpandedType": 0,
  "name": "list / messages / messageListEach",
  "nameIsFixed": false,
  "overrideValues": [
    {
      "_class": "overrideValue",
      "do_objectID": "7FF035A1-6E99-4EDF-A7E4-655B6742BDEB",
      "overrideName": "F7A26C5F-D453-42A1-A9BF-3F842448AC06/97D12EC3-F4BD-4A8F-BC7D-6F35D1FF5E35/0A79F754-4172-444B-B77A-582B24D5BD29_image",
      "value": {
        "_class": "MSJSONFileReference",
        "_ref": "images/188a8e10806efa1ed5c80b5eb5567978e831e031.png",
        "_ref_class": "MSImageData"
      }
    }
  ],
  "resizingConstraint": 13,
  "resizingType": 0,
  "rotation": 0,
  "scale": 1,
  "shouldBreakMaskChain": false,
  "style": {
    "_class": "style",
    "do_objectID": "51C184C7-D6B5-496B-9ADD-1D4904B0227A",
    "endMarkerType": 0,
    "miterLimit": 10,
    "startMarkerType": 0,
    "windingRule": 1
  },
  "symbolID": "A450B82C-9F00-43F0-8540-8A333F1D3195",
  "verticalSpacing": 0
}